{
  "metadata": {
    "analysis_timestamp": "2025-08-10T00:23:38.842527+00:00",
    "duration_minutes": 2,
    "sample_interval_seconds": 10,
    "total_samples": 12,
    "total_operations": 521
  },
  "analysis_results": {
    "duration_minutes": 2,
    "sample_count": 12,
    "memory_statistics": {
      "initial_mb": 54.25,
      "final_mb": 55.05859375,
      "peak_mb": 55.1328125,
      "min_mb": 54.25,
      "avg_mb": 54.937825520833336,
      "memory_growth_mb": 0.80859375,
      "growth_rate_mb_per_hour": 24.2578125
    },
    "trend_analysis": {
      "slope_mb_per_sample": 0.03896689248251748,
      "correlation_coefficient": 0.5831389159867679,
      "trend_strength": 0.5831389159867679,
      "trend_direction": "increasing"
    },
    "stability_analysis": {
      "standard_deviation_mb": 0.24093252060439932,
      "coefficient_of_variation": 0.004385548905881499,
      "stability_score": 0.9956144510941185,
      "memory_spikes_count": 0,
      "largest_spike_mb": 0,
      "is_stable": true
    },
    "gc_analysis": {
      "total_objects_reclaimed": 50,
      "avg_objects_per_gc": 4.166666666666667,
      "total_memory_freed_mb": -3.02734375,
      "avg_memory_freed_mb": -0.2522786458333333,
      "gc_samples": 12,
      "gc_effectiveness_score": 0.004166666666666667
    },
    "health_assessment": {
      "status": "\u274c Leak Detected",
      "health_score": 55,
      "leak_indicators": [
        "High growth rate: 24.3 MB/hour",
        "Poor GC effectiveness: 0.00"
      ],
      "recommendation": "Memory leak detected, investigation required",
      "growth_rate_mb_per_hour": 24.2578125,
      "peak_to_baseline_ratio": 1.0162730414746544,
      "memory_stability": true
    },
    "operations_completed": 521,
    "thresholds": {
      "leak_growth_mb_per_hour": 5.0,
      "peak_to_baseline_ratio": 2.0,
      "gc_effectiveness_threshold": 0.8,
      "memory_stability_threshold": 0.9
    }
  },
  "raw_samples": [
    {
      "timestamp": "2025-08-10T00:21:34.588235+00:00",
      "elapsed_seconds": -9.5367431640625e-07,
      "process_memory_mb": 54.25,
      "process_memory_vms_mb": 49.70703125,
      "memory_percent": 0.08296621916403768,
      "system_memory_total_gb": 63.855525970458984,
      "system_memory_available_gb": 21.103763580322266,
      "system_memory_percent": 67.0,
      "gc_objects_before": 51929,
      "gc_objects_after": 51901,
      "gc_objects_reclaimed": 28,
      "memory_freed_by_gc_mb": 0.2890625,
      "cpu_percent": 0.0,
      "num_threads": 5
    },
    {
      "timestamp": "2025-08-10T00:21:44.954383+00:00",
      "elapsed_seconds": 9.999999284744263,
      "process_memory_mb": 55.1328125,
      "process_memory_vms_mb": 50.48828125,
      "memory_percent": 0.08431633188948934,
      "system_memory_total_gb": 63.855525970458984,
      "system_memory_available_gb": 23.359703063964844,
      "system_memory_percent": 63.4,
      "gc_objects_before": 51968,
      "gc_objects_after": 51962,
      "gc_objects_reclaimed": 6,
      "memory_freed_by_gc_mb": -0.171875,
      "cpu_percent": 0.0,
      "num_threads": 5
    },
    {
      "timestamp": "2025-08-10T00:21:55.214984+00:00",
      "elapsed_seconds": 19.999998331069946,
      "process_memory_mb": 54.94921875,
      "process_memory_vms_mb": 50.51171875,
      "memory_percent": 0.08403555623419628,
      "system_memory_total_gb": 63.855525970458984,
      "system_memory_available_gb": 19.889328002929688,
      "system_memory_percent": 68.9,
      "gc_objects_before": 51998,
      "gc_objects_after": 51997,
      "gc_objects_reclaimed": 1,
      "memory_freed_by_gc_mb": -0.69140625,
      "cpu_percent": 0.0,
      "num_threads": 7
    },
    {
      "timestamp": "2025-08-10T00:22:05.521088+00:00",
      "elapsed_seconds": 29.999999046325684,
      "process_memory_mb": 54.8203125,
      "process_memory_vms_mb": 50.515625,
      "memory_percent": 0.0838384158804799,
      "system_memory_total_gb": 63.855525970458984,
      "system_memory_available_gb": 20.192310333251953,
      "system_memory_percent": 68.4,
      "gc_objects_before": 52040,
      "gc_objects_after": 52039,
      "gc_objects_reclaimed": 1,
      "memory_freed_by_gc_mb": -0.29296875,
      "cpu_percent": 0.0,
      "num_threads": 7
    },
    {
      "timestamp": "2025-08-10T00:22:15.794398+00:00",
      "elapsed_seconds": 39.99999952316284,
      "process_memory_mb": 54.94921875,
      "process_memory_vms_mb": 50.50390625,
      "memory_percent": 0.08403555623419628,
      "system_memory_total_gb": 63.855525970458984,
      "system_memory_available_gb": 22.393749237060547,
      "system_memory_percent": 64.9,
      "gc_objects_before": 51888,
      "gc_objects_after": 51887,
      "gc_objects_reclaimed": 1,
      "memory_freed_by_gc_mb": -0.265625,
      "cpu_percent": 0.0,
      "num_threads": 7
    },
    {
      "timestamp": "2025-08-10T00:22:26.091581+00:00",
      "elapsed_seconds": 49.99999952316284,
      "process_memory_mb": 54.8125,
      "process_memory_vms_mb": 50.4296875,
      "memory_percent": 0.08382646798025466,
      "system_memory_total_gb": 63.855525970458984,
      "system_memory_available_gb": 19.596603393554688,
      "system_memory_percent": 69.3,
      "gc_objects_before": 51936,
      "gc_objects_after": 51935,
      "gc_objects_reclaimed": 1,
      "memory_freed_by_gc_mb": -0.32421875,
      "cpu_percent": 0.0,
      "num_threads": 5
    },
    {
      "timestamp": "2025-08-10T00:22:36.292575+00:00",
      "elapsed_seconds": 59.99999952316284,
      "process_memory_mb": 55.05859375,
      "process_memory_vms_mb": 50.48046875,
      "memory_percent": 0.08420282683734959,
      "system_memory_total_gb": 63.855525970458984,
      "system_memory_available_gb": 20.655670166015625,
      "system_memory_percent": 67.7,
      "gc_objects_before": 51985,
      "gc_objects_after": 51985,
      "gc_objects_reclaimed": 0,
      "memory_freed_by_gc_mb": -0.30859375,
      "cpu_percent": 0.0,
      "num_threads": 5
    },
    {
      "timestamp": "2025-08-10T00:22:46.606622+00:00",
      "elapsed_seconds": 69.99999904632568,
      "process_memory_mb": 54.96484375,
      "process_memory_vms_mb": 50.44140625,
      "memory_percent": 0.08405945203464676,
      "system_memory_total_gb": 63.855525970458984,
      "system_memory_available_gb": 20.893898010253906,
      "system_memory_percent": 67.3,
      "gc_objects_before": 52039,
      "gc_objects_after": 52038,
      "gc_objects_reclaimed": 1,
      "memory_freed_by_gc_mb": -0.28515625,
      "cpu_percent": 0.0,
      "num_threads": 5
    },
    {
      "timestamp": "2025-08-10T00:22:57.098762+00:00",
      "elapsed_seconds": 79.99999928474426,
      "process_memory_mb": 55.07421875,
      "process_memory_vms_mb": 50.4609375,
      "memory_percent": 0.08422672263780007,
      "system_memory_total_gb": 63.855525970458984,
      "system_memory_available_gb": 21.581951141357422,
      "system_memory_percent": 66.2,
      "gc_objects_before": 52077,
      "gc_objects_after": 52076,
      "gc_objects_reclaimed": 1,
      "memory_freed_by_gc_mb": -0.2734375,
      "cpu_percent": 0.0,
      "num_threads": 5
    },
    {
      "timestamp": "2025-08-10T00:23:07.594920+00:00",
      "elapsed_seconds": 89.99999952316284,
      "process_memory_mb": 55.0625,
      "process_memory_vms_mb": 50.390625,
      "memory_percent": 0.0842088007874622,
      "system_memory_total_gb": 63.855525970458984,
      "system_memory_available_gb": 19.3077392578125,
      "system_memory_percent": 69.8,
      "gc_objects_before": 51923,
      "gc_objects_after": 51920,
      "gc_objects_reclaimed": 3,
      "memory_freed_by_gc_mb": -0.20703125,
      "cpu_percent": 0.0,
      "num_threads": 5
    },
    {
      "timestamp": "2025-08-10T00:23:17.897750+00:00",
      "elapsed_seconds": 99.99999952316284,
      "process_memory_mb": 55.12109375,
      "process_memory_vms_mb": 50.44140625,
      "memory_percent": 0.08429841003915148,
      "system_memory_total_gb": 63.855525970458984,
      "system_memory_available_gb": 19.17369842529297,
      "system_memory_percent": 70.0,
      "gc_objects_before": 51949,
      "gc_objects_after": 51948,
      "gc_objects_reclaimed": 1,
      "memory_freed_by_gc_mb": -0.1875,
      "cpu_percent": 0.0,
      "num_threads": 5
    },
    {
      "timestamp": "2025-08-10T00:23:28.637847+00:00",
      "elapsed_seconds": 109.99999952316284,
      "process_memory_mb": 55.05859375,
      "process_memory_vms_mb": 50.48828125,
      "memory_percent": 0.08420282683734959,
      "system_memory_total_gb": 63.855525970458984,
      "system_memory_available_gb": 21.31704330444336,
      "system_memory_percent": 66.6,
      "gc_objects_before": 52007,
      "gc_objects_after": 52001,
      "gc_objects_reclaimed": 6,
      "memory_freed_by_gc_mb": -0.30859375,
      "cpu_percent": 0.0,
      "num_threads": 5
    }
  ],
  "thresholds": {
    "leak_growth_mb_per_hour": 5.0,
    "peak_to_baseline_ratio": 2.0,
    "gc_effectiveness_threshold": 0.8,
    "memory_stability_threshold": 0.9
  }
}